jupyter_dojo/__init__.py
jupyter_dojo/jupyter_dojo-labextension-0.1.1.tgz
jupyter_dojo/static/extension.js
jupyter_dojo/static/extension.js.map
jupyter_dojo/static/index.js
jupyter_dojo/static/index.js.map
jupyter_dojo/static/package.json
jupyter_dojo-0.3.2.data/data/share/jupyter/lab/extensions/jupyter_dojo-labextension-0.1.1.tgz
jupyter_dojo-0.3.2.data/data/share/jupyter/nbextensions/jupyter_dojo/extension.js
jupyter_dojo-0.3.2.data/data/share/jupyter/nbextensions/jupyter_dojo/extension.js.map
jupyter_dojo-0.3.2.data/data/share/jupyter/nbextensions/jupyter_dojo/index.js
jupyter_dojo-0.3.2.data/data/share/jupyter/nbextensions/jupyter_dojo/index.js.map
jupyter_dojo-0.3.2.data/data/share/jupyter/nbextensions/jupyter_dojo/package.json
jupyter_dojo-0.3.2.dist-info/DESCRIPTION.rst
jupyter_dojo-0.3.2.dist-info/METADATA
jupyter_dojo-0.3.2.dist-info/RECORD
jupyter_dojo-0.3.2.dist-info/WHEEL
jupyter_dojo-0.3.2.dist-info/metadata.json
jupyter_dojo-0.3.2.dist-info/top_level.txt
