Metadata-Version: 2.0
Name: jupyter-dojo
Version: 0.3.2
Summary: A JupyterLab and Jupyter Notebook extension for rendering unittest results
Home-page: https://github.com/JoaoFelipe/jupyter-dojo
Author: Joao Felipe Pimentel
Author-email: joaofelipenp@gmail.com
License: MIT
Keywords: ipython,jupyter
Platform: Linux
Platform: Mac OS X
Platform: Windows
Classifier: Intended Audience :: Developers
Classifier: Intended Audience :: System Administrators
Classifier: Intended Audience :: Science/Research
Classifier: License :: OSI Approved :: MIT License
Classifier: Programming Language :: Python
Classifier: Programming Language :: Python :: 2.7
Classifier: Programming Language :: Python :: 3
Classifier: Programming Language :: Python :: 3.3
Classifier: Programming Language :: Python :: 3.4
Classifier: Programming Language :: Python :: 3.5
Requires-Dist: ipython (>=1.0.0)
Requires-Dist: ipython-unittest (>=0.3.0)
Requires-Dist: notebook (>=4.3.0)
